Workbook

Sheet Rekap
A1: KaataGo — Rekap Pengujian
A2: Angkanya menghitung sendiri dari lembar Kasus Uji.
A4: Kelompok | B4: Jumlah | C4: Lulus | D4: Gagal | E4: Terblokir | F4: Dilewati | G4: Belum diuji
A5: Prioritas P1 | B5: =COUNTIF('Kasus Uji'!C2:C332,"P1") | C5: =COUNTIFS('Kasus Uji'!C2:C332,"P1",'Kasus Uji'!G2:G332,"Lulus") | D5: =COUNTIFS('Kasus Uji'!C2:C332,"P1",'Kasus Uji'!G2:G332,"Gagal") | E5: =COUNTIFS('Kasus Uji'!C2:C332,"P1",'Kasus Uji'!G2:G332,"Terblokir") | F5: =COUNTIFS('Kasus Uji'!C2:C332,"P1",'Kasus Uji'!G2:G332,"Dilewati") | G5: =B5-SUM(C5:F5)
A6: Prioritas P2 | B6: =COUNTIF('Kasus Uji'!C2:C332,"P2") | C6: =COUNTIFS('Kasus Uji'!C2:C332,"P2",'Kasus Uji'!G2:G332,"Lulus") | D6: =COUNTIFS('Kasus Uji'!C2:C332,"P2",'Kasus Uji'!G2:G332,"Gagal") | E6: =COUNTIFS('Kasus Uji'!C2:C332,"P2",'Kasus Uji'!G2:G332,"Terblokir") | F6: =COUNTIFS('Kasus Uji'!C2:C332,"P2",'Kasus Uji'!G2:G332,"Dilewati") | G6: =B6-SUM(C6:F6)
A7: Prioritas P3 | B7: =COUNTIF('Kasus Uji'!C2:C332,"P3") | C7: =COUNTIFS('Kasus Uji'!C2:C332,"P3",'Kasus Uji'!G2:G332,"Lulus") | D7: =COUNTIFS('Kasus Uji'!C2:C332,"P3",'Kasus Uji'!G2:G332,"Gagal") | E7: =COUNTIFS('Kasus Uji'!C2:C332,"P3",'Kasus Uji'!G2:G332,"Terblokir") | F7: =COUNTIFS('Kasus Uji'!C2:C332,"P3",'Kasus Uji'!G2:G332,"Dilewati") | G7: =B7-SUM(C7:F7)
A8: TOTAL | B8: =SUM(B5:B7) | C8: =SUM(C5:C7) | D8: =SUM(D5:D7) | E8: =SUM(E5:E7) | F8: =SUM(F5:F7) | G8: =SUM(G5:G7)
A10: Per modul
A11: Kelompok | B11: Jumlah | C11: Lulus | D11: Gagal | E11: Terblokir | F11: Dilewati | G11: Belum diuji
A12: Pelanggan | B12: =COUNTIF('Kasus Uji'!A2:A332,"Pelanggan") | C12: =COUNTIFS('Kasus Uji'!A2:A332,"Pelanggan",'Kasus Uji'!G2:G332,"Lulus") | D12: =COUNTIFS('Kasus Uji'!A2:A332,"Pelanggan",'Kasus Uji'!G2:G332,"Gagal") | E12: =COUNTIFS('Kasus Uji'!A2:A332,"Pelanggan",'Kasus Uji'!G2:G332,"Terblokir") | F12: =COUNTIFS('Kasus Uji'!A2:A332,"Pelanggan",'Kasus Uji'!G2:G332,"Dilewati") | G12: =B12-SUM(C12:F12)
A13: Kasir | B13: =COUNTIF('Kasus Uji'!A2:A332,"Kasir") | C13: =COUNTIFS('Kasus Uji'!A2:A332,"Kasir",'Kasus Uji'!G2:G332,"Lulus") | D13: =COUNTIFS('Kasus Uji'!A2:A332,"Kasir",'Kasus Uji'!G2:G332,"Gagal") | E13: =COUNTIFS('Kasus Uji'!A2:A332,"Kasir",'Kasus Uji'!G2:G332,"Terblokir") | F13: =COUNTIFS('Kasus Uji'!A2:A332,"Kasir",'Kasus Uji'!G2:G332,"Dilewati") | G13: =B13-SUM(C13:F13)
A14: Pending Payment | B14: =COUNTIF('Kasus Uji'!A2:A332,"Pending Payment") | C14: =COUNTIFS('Kasus Uji'!A2:A332,"Pending Payment",'Kasus Uji'!G2:G332,"Lulus") | D14: =COUNTIFS('Kasus Uji'!A2:A332,"Pending Payment",'Kasus Uji'!G2:G332,"Gagal") | E14: =COUNTIFS('Kasus Uji'!A2:A332,"Pending Payment",'Kasus Uji'!G2:G332,"Terblokir") | F14: =COUNTIFS('Kasus Uji'!A2:A332,"Pending Payment",'Kasus Uji'!G2:G332,"Dilewati") | G14: =B14-SUM(C14:F14)
A15: Dapur | B15: =COUNTIF('Kasus Uji'!A2:A332,"Dapur") | C15: =COUNTIFS('Kasus Uji'!A2:A332,"Dapur",'Kasus Uji'!G2:G332,"Lulus") | D15: =COUNTIFS('Kasus Uji'!A2:A332,"Dapur",'Kasus Uji'!G2:G332,"Gagal") | E15: =COUNTIFS('Kasus Uji'!A2:A332,"Dapur",'Kasus Uji'!G2:G332,"Terblokir") | F15: =COUNTIFS('Kasus Uji'!A2:A332,"Dapur",'Kasus Uji'!G2:G332,"Dilewati") | G15: =B15-SUM(C15:F15)
A16: Keuangan | B16: =COUNTIF('Kasus Uji'!A2:A332,"Keuangan") | C16: =COUNTIFS('Kasus Uji'!A2:A332,"Keuangan",'Kasus Uji'!G2:G332,"Lulus") | D16: =COUNTIFS('Kasus Uji'!A2:A332,"Keuangan",'Kasus Uji'!G2:G332,"Gagal") | E16: =COUNTIFS('Kasus Uji'!A2:A332,"Keuangan",'Kasus Uji'!G2:G332,"Terblokir") | F16: =COUNTIFS('Kasus Uji'!A2:A332,"Keuangan",'Kasus Uji'!G2:G332,"Dilewati") | G16: =B16-SUM(C16:F16)
A17: Setor Saldo Cash | B17: =COUNTIF('Kasus Uji'!A2:A332,"Setor Saldo Cash") | C17: =COUNTIFS('Kasus Uji'!A2:A332,"Setor Saldo Cash",'Kasus Uji'!G2:G332,"Lulus") | D17: =COUNTIFS('Kasus Uji'!A2:A332,"Setor Saldo Cash",'Kasus Uji'!G2:G332,"Gagal") | E17: =COUNTIFS('Kasus Uji'!A2:A332,"Setor Saldo Cash",'Kasus Uji'!G2:G332,"Terblokir") | F17: =COUNTIFS('Kasus Uji'!A2:A332,"Setor Saldo Cash",'Kasus Uji'!G2:G332,"Dilewati") | G17: =B17-SUM(C17:F17)
A18: Katalog & Pengaturan | B18: =COUNTIF('Kasus Uji'!A2:A332,"Katalog & Pengaturan") | C18: =COUNTIFS('Kasus Uji'!A2:A332,"Katalog & Pengaturan",'Kasus Uji'!G2:G332,"Lulus") | D18: =COUNTIFS('Kasus Uji'!A2:A332,"Katalog & Pengaturan",'Kasus Uji'!G2:G332,"Gagal") | E18: =COUNTIFS('Kasus Uji'!A2:A332,"Katalog & Pengaturan",'Kasus Uji'!G2:G332,"Terblokir") | F18: =COUNTIFS('Kasus Uji'!A2:A332,"Katalog & Pengaturan",'Kasus Uji'!G2:G332,"Dilewati") | G18: =B18-SUM(C18:F18)
A19: QR Meja | B19: =COUNTIF('Kasus Uji'!A2:A332,"QR Meja") | C19: =COUNTIFS('Kasus Uji'!A2:A332,"QR Meja",'Kasus Uji'!G2:G332,"Lulus") | D19: =COUNTIFS('Kasus Uji'!A2:A332,"QR Meja",'Kasus Uji'!G2:G332,"Gagal") | E19: =COUNTIFS('Kasus Uji'!A2:A332,"QR Meja",'Kasus Uji'!G2:G332,"Terblokir") | F19: =COUNTIFS('Kasus Uji'!A2:A332,"QR Meja",'Kasus Uji'!G2:G332,"Dilewati") | G19: =B19-SUM(C19:F19)
A20: Diskon | B20: =COUNTIF('Kasus Uji'!A2:A332,"Diskon") | C20: =COUNTIFS('Kasus Uji'!A2:A332,"Diskon",'Kasus Uji'!G2:G332,"Lulus") | D20: =COUNTIFS('Kasus Uji'!A2:A332,"Diskon",'Kasus Uji'!G2:G332,"Gagal") | E20: =COUNTIFS('Kasus Uji'!A2:A332,"Diskon",'Kasus Uji'!G2:G332,"Terblokir") | F20: =COUNTIFS('Kasus Uji'!A2:A332,"Diskon",'Kasus Uji'!G2:G332,"Dilewati") | G20: =B20-SUM(C20:F20)
A21: Kotak Masuk & Pengumuman | B21: =COUNTIF('Kasus Uji'!A2:A332,"Kotak Masuk & Pengumuman") | C21: =COUNTIFS('Kasus Uji'!A2:A332,"Kotak Masuk & Pengumuman",'Kasus Uji'!G2:G332,"Lulus") | D21: =COUNTIFS('Kasus Uji'!A2:A332,"Kotak Masuk & Pengumuman",'Kasus Uji'!G2:G332,"Gagal") | E21: =COUNTIFS('Kasus Uji'!A2:A332,"Kotak Masuk & Pengumuman",'Kasus Uji'!G2:G332,"Terblokir") | F21: =COUNTIFS('Kasus Uji'!A2:A332,"Kotak Masuk & Pengumuman",'Kasus Uji'!G2:G332,"Dilewati") | G21: =B21-SUM(C21:F21)
A22: Pembayaran QRIS | B22: =COUNTIF('Kasus Uji'!A2:A332,"Pembayaran QRIS") | C22: =COUNTIFS('Kasus Uji'!A2:A332,"Pembayaran QRIS",'Kasus Uji'!G2:G332,"Lulus") | D22: =COUNTIFS('Kasus Uji'!A2:A332,"Pembayaran QRIS",'Kasus Uji'!G2:G332,"Gagal") | E22: =COUNTIFS('Kasus Uji'!A2:A332,"Pembayaran QRIS",'Kasus Uji'!G2:G332,"Terblokir") | F22: =COUNTIFS('Kasus Uji'!A2:A332,"Pembayaran QRIS",'Kasus Uji'!G2:G332,"Dilewati") | G22: =B22-SUM(C22:F22)
A23: Pembatalan & Kedaluwarsa | B23: =COUNTIF('Kasus Uji'!A2:A332,"Pembatalan & Kedaluwarsa") | C23: =COUNTIFS('Kasus Uji'!A2:A332,"Pembatalan & Kedaluwarsa",'Kasus Uji'!G2:G332,"Lulus") | D23: =COUNTIFS('Kasus Uji'!A2:A332,"Pembatalan & Kedaluwarsa",'Kasus Uji'!G2:G332,"Gagal") | E23: =COUNTIFS('Kasus Uji'!A2:A332,"Pembatalan & Kedaluwarsa",'Kasus Uji'!G2:G332,"Terblokir") | F23: =COUNTIFS('Kasus Uji'!A2:A332,"Pembatalan & Kedaluwarsa",'Kasus Uji'!G2:G332,"Dilewati") | G23: =B23-SUM(C23:F23)
A24: Sesi Meja & Identitas | B24: =COUNTIF('Kasus Uji'!A2:A332,"Sesi Meja & Identitas") | C24: =COUNTIFS('Kasus Uji'!A2:A332,"Sesi Meja & Identitas",'Kasus Uji'!G2:G332,"Lulus") | D24: =COUNTIFS('Kasus Uji'!A2:A332,"Sesi Meja & Identitas",'Kasus Uji'!G2:G332,"Gagal") | E24: =COUNTIFS('Kasus Uji'!A2:A332,"Sesi Meja & Identitas",'Kasus Uji'!G2:G332,"Terblokir") | F24: =COUNTIFS('Kasus Uji'!A2:A332,"Sesi Meja & Identitas",'Kasus Uji'!G2:G332,"Dilewati") | G24: =B24-SUM(C24:F24)
A25: Tampilan | B25: =COUNTIF('Kasus Uji'!A2:A332,"Tampilan") | C25: =COUNTIFS('Kasus Uji'!A2:A332,"Tampilan",'Kasus Uji'!G2:G332,"Lulus") | D25: =COUNTIFS('Kasus Uji'!A2:A332,"Tampilan",'Kasus Uji'!G2:G332,"Gagal") | E25: =COUNTIFS('Kasus Uji'!A2:A332,"Tampilan",'Kasus Uji'!G2:G332,"Terblokir") | F25: =COUNTIFS('Kasus Uji'!A2:A332,"Tampilan",'Kasus Uji'!G2:G332,"Dilewati") | G25: =B25-SUM(C25:F25)
A26: Super Admin | B26: =COUNTIF('Kasus Uji'!A2:A332,"Super Admin") | C26: =COUNTIFS('Kasus Uji'!A2:A332,"Super Admin",'Kasus Uji'!G2:G332,"Lulus") | D26: =COUNTIFS('Kasus Uji'!A2:A332,"Super Admin",'Kasus Uji'!G2:G332,"Gagal") | E26: =COUNTIFS('Kasus Uji'!A2:A332,"Super Admin",'Kasus Uji'!G2:G332,"Terblokir") | F26: =COUNTIFS('Kasus Uji'!A2:A332,"Super Admin",'Kasus Uji'!G2:G332,"Dilewati") | G26: =B26-SUM(C26:F26)
A27: Pembaruan Aplikasi | B27: =COUNTIF('Kasus Uji'!A2:A332,"Pembaruan Aplikasi") | C27: =COUNTIFS('Kasus Uji'!A2:A332,"Pembaruan Aplikasi",'Kasus Uji'!G2:G332,"Lulus") | D27: =COUNTIFS('Kasus Uji'!A2:A332,"Pembaruan Aplikasi",'Kasus Uji'!G2:G332,"Gagal") | E27: =COUNTIFS('Kasus Uji'!A2:A332,"Pembaruan Aplikasi",'Kasus Uji'!G2:G332,"Terblokir") | F27: =COUNTIFS('Kasus Uji'!A2:A332,"Pembaruan Aplikasi",'Kasus Uji'!G2:G332,"Dilewati") | G27: =B27-SUM(C27:F27)
A28: ## 19b. Langganan & Tagihan Resto | B28: =COUNTIF('Kasus Uji'!A2:A332,"## 19b. Langganan & Tagihan Resto") | C28: =COUNTIFS('Kasus Uji'!A2:A332,"## 19b. Langganan & Tagihan Resto",'Kasus Uji'!G2:G332,"Lulus") | D28: =COUNTIFS('Kasus Uji'!A2:A332,"## 19b. Langganan & Tagihan Resto",'Kasus Uji'!G2:G332,"Gagal") | E28: =COUNTIFS('Kasus Uji'!A2:A332,"## 19b. Langganan & Tagihan Resto",'Kasus Uji'!G2:G332,"Terblokir") | F28: =COUNTIFS('Kasus Uji'!A2:A332,"## 19b. Langganan & Tagihan Resto",'Kasus Uji'!G2:G332,"Dilewati") | G28: =B28-SUM(C28:F28)
A29: ## 19c. Finance KaataGo (Super Admin) | B29: =COUNTIF('Kasus Uji'!A2:A332,"## 19c. Finance KaataGo (Super Admin)") | C29: =COUNTIFS('Kasus Uji'!A2:A332,"## 19c. Finance KaataGo (Super Admin)",'Kasus Uji'!G2:G332,"Lulus") | D29: =COUNTIFS('Kasus Uji'!A2:A332,"## 19c. Finance KaataGo (Super Admin)",'Kasus Uji'!G2:G332,"Gagal") | E29: =COUNTIFS('Kasus Uji'!A2:A332,"## 19c. Finance KaataGo (Super Admin)",'Kasus Uji'!G2:G332,"Terblokir") | F29: =COUNTIFS('Kasus Uji'!A2:A332,"## 19c. Finance KaataGo (Super Admin)",'Kasus Uji'!G2:G332,"Dilewati") | G29: =B29-SUM(C29:F29)
A30: Uji Teknis (lingkup TSD) | B30: =COUNTIF('Kasus Uji'!A2:A332,"Uji Teknis (lingkup TSD)") | C30: =COUNTIFS('Kasus Uji'!A2:A332,"Uji Teknis (lingkup TSD)",'Kasus Uji'!G2:G332,"Lulus") | D30: =COUNTIFS('Kasus Uji'!A2:A332,"Uji Teknis (lingkup TSD)",'Kasus Uji'!G2:G332,"Gagal") | E30: =COUNTIFS('Kasus Uji'!A2:A332,"Uji Teknis (lingkup TSD)",'Kasus Uji'!G2:G332,"Terblokir") | F30: =COUNTIFS('Kasus Uji'!A2:A332,"Uji Teknis (lingkup TSD)",'Kasus Uji'!G2:G332,"Dilewati") | G30: =B30-SUM(C30:F30)
A31: Regresi — bug yang pernah terjadi | B31: =COUNTIF('Kasus Uji'!A2:A332,"Regresi — bug yang pernah terjadi") | C31: =COUNTIFS('Kasus Uji'!A2:A332,"Regresi — bug yang pernah terjadi",'Kasus Uji'!G2:G332,"Lulus") | D31: =COUNTIFS('Kasus Uji'!A2:A332,"Regresi — bug yang pernah terjadi",'Kasus Uji'!G2:G332,"Gagal") | E31: =COUNTIFS('Kasus Uji'!A2:A332,"Regresi — bug yang pernah terjadi",'Kasus Uji'!G2:G332,"Terblokir") | F31: =COUNTIFS('Kasus Uji'!A2:A332,"Regresi — bug yang pernah terjadi",'Kasus Uji'!G2:G332,"Dilewati") | G31: =B31-SUM(C31:F31)
A32: Uji Ujung-ke-Ujung | B32: =COUNTIF('Kasus Uji'!A2:A332,"Uji Ujung-ke-Ujung") | C32: =COUNTIFS('Kasus Uji'!A2:A332,"Uji Ujung-ke-Ujung",'Kasus Uji'!G2:G332,"Lulus") | D32: =COUNTIFS('Kasus Uji'!A2:A332,"Uji Ujung-ke-Ujung",'Kasus Uji'!G2:G332,"Gagal") | E32: =COUNTIFS('Kasus Uji'!A2:A332,"Uji Ujung-ke-Ujung",'Kasus Uji'!G2:G332,"Terblokir") | F32: =COUNTIFS('Kasus Uji'!A2:A332,"Uji Ujung-ke-Ujung",'Kasus Uji'!G2:G332,"Dilewati") | G32: =B32-SUM(C32:F32)
A34: Rilis ditahan selama masih ada P1 yang Gagal.
A36: Temuan
A37: Severity | B37: Jumlah | C37: Baru | D37: Dikonfirmasi | E37: Sedang diperbaiki | F37: Menunggu retest | G37: Ditutup
A38: Blocker | B38: =COUNTIF(Defect!M5:M64,"Blocker") | C38: =COUNTIFS(Defect!M5:M64,"Blocker",Defect!P5:P64,"Baru") | D38: =COUNTIFS(Defect!M5:M64,"Blocker",Defect!P5:P64,"Dikonfirmasi") | E38: =COUNTIFS(Defect!M5:M64,"Blocker",Defect!P5:P64,"Sedang diperbaiki") | F38: =COUNTIFS(Defect!M5:M64,"Blocker",Defect!P5:P64,"Menunggu retest") | G38: =COUNTIFS(Defect!M5:M64,"Blocker",Defect!P5:P64,"Ditutup")
A39: Major | B39: =COUNTIF(Defect!M5:M64,"Major") | C39: =COUNTIFS(Defect!M5:M64,"Major",Defect!P5:P64,"Baru") | D39: =COUNTIFS(Defect!M5:M64,"Major",Defect!P5:P64,"Dikonfirmasi") | E39: =COUNTIFS(Defect!M5:M64,"Major",Defect!P5:P64,"Sedang diperbaiki") | F39: =COUNTIFS(Defect!M5:M64,"Major",Defect!P5:P64,"Menunggu retest") | G39: =COUNTIFS(Defect!M5:M64,"Major",Defect!P5:P64,"Ditutup")
A40: Minor | B40: =COUNTIF(Defect!M5:M64,"Minor") | C40: =COUNTIFS(Defect!M5:M64,"Minor",Defect!P5:P64,"Baru") | D40: =COUNTIFS(Defect!M5:M64,"Minor",Defect!P5:P64,"Dikonfirmasi") | E40: =COUNTIFS(Defect!M5:M64,"Minor",Defect!P5:P64,"Sedang diperbaiki") | F40: =COUNTIFS(Defect!M5:M64,"Minor",Defect!P5:P64,"Menunggu retest") | G40: =COUNTIFS(Defect!M5:M64,"Minor",Defect!P5:P64,"Ditutup")
A41: Trivial | B41: =COUNTIF(Defect!M5:M64,"Trivial") | C41: =COUNTIFS(Defect!M5:M64,"Trivial",Defect!P5:P64,"Baru") | D41: =COUNTIFS(Defect!M5:M64,"Trivial",Defect!P5:P64,"Dikonfirmasi") | E41: =COUNTIFS(Defect!M5:M64,"Trivial",Defect!P5:P64,"Sedang diperbaiki") | F41: =COUNTIFS(Defect!M5:M64,"Trivial",Defect!P5:P64,"Menunggu retest") | G41: =COUNTIFS(Defect!M5:M64,"Trivial",Defect!P5:P64,"Ditutup")
A42: TOTAL | B42: =SUM(B38:B41) | C42: =SUM(C38:C41) | D42: =SUM(D38:D41) | E42: =SUM(E38:E41) | F42: =SUM(F38:F41) | G42: =SUM(G38:G41)
A44: Blocker yang belum Ditutup menahan rilis.

Sheet Kasus Uji
A1: Modul | B1: ID | C1: P | D1: Skenario / Langkah | E1: Hasil yang Diharapkan | F1: Rujukan | G1: Hasil | H1: Catatan | I1: Diuji Oleh
A2: Pelanggan | B2: TC-CU-01 | C2: P1 | D2: Buka aplikasi → Pelanggan → Lewati, Pesan Tanpa Login → pesan sampai selesai | E2: Seluruh alur bisa dituntaskan tanpa membuat akun | F2: F-CU-01, A-01
A3: Pelanggan | B3: TC-CU-02 | C3: P1 | D3: Scan QR meja sebuah resto | E3: Menu resto terbuka, nomor meja terisi sendiri dan tidak bisa diubah | F3: F-CU-02, F-CU-03
A4: Pelanggan | B4: TC-CU-03 | C4: P2 | D4: Pilih Resto tanpa memberi izin lokasi | E4: Hanya bagian Semua Resto tampil; tidak ada galat, tidak ada bagian kosong berjudul "Terdekat" | F4: F-CU-02
A5: Pelanggan | B5: TC-CU-04 | C5: P2 | D5: Beri izin lokasi, buka Pilih Resto lagi | E5: Bagian Terdekat muncul berikut jarak tiap resto | F5: F-CU-02
A6: Pelanggan | B6: TC-CU-05 | C6: P2 | D6: Cari resto dengan potongan alamat, bukan namanya | E6: Resto yang alamatnya cocok ikut muncul | F6: F-CU-02
A7: Pelanggan | B7: TC-CU-06 | C7: P2 | D7: Buka menu minuman yang punya tiga kelompok level | E7: Ketiga kelompok tampil sekaligus; tiap kelompok wajib dipilih | F7: F-CU-04
A8: Pelanggan | B8: TC-CU-07 | C8: P2 | D8: Tambahkan Nasi Goreng "Pedas", lalu Nasi Goreng "Tidak Pedas" | E8: Keranjang berisi dua baris terpisah, bukan satu baris berjumlah 2 | F8: F-CU-05
A9: Pelanggan | B9: TC-CU-08 | C9: P2 | D9: Tambahkan menu yang sama dengan level dan catatan persis sama, dua kali | E9: Menyatu jadi satu baris berjumlah 2 | F9: F-CU-05
A10: Pelanggan | B10: TC-CU-09 | C10: P2 | D10: Ubah jumlah dan hapus baris dari keranjang | E10: Subtotal dan total ikut berubah seketika | F10: F-CU-06
A11: Pelanggan | B11: TC-CU-10 | C11: P1 | D11: Pilih Take Away | E11: Nomor meja tidak diminta; nama pemesan tetap wajib | F11: F-CU-07, F-CU-08
A12: Pelanggan | B12: TC-CU-11 | C12: P1 | D12: Pilih Dine In, kosongkan nomor meja | E12: Tombol bayar mati; petunjuknya menyebut kolom mana yang kurang | F12: F-CU-07
A13: Pelanggan | B13: TC-CU-12 | C13: P1 | D13: Periksa ringkasan tagihan | E13: Subtotal + biaya service + PPN = total, persis, tanpa selisih pembulatan | F13: F-CU-10, A-04
... A332: Uji Ujung-ke-Ujung | B332: E2E-08 | C332: P1 | D332: Isolasi antar cabang | E332: 1. Dengan akun Owner yang memiliki dua resto: buat transaksi, promo, dan 2. pengumuman di resto A, lalu berpindah ke resto B. Tidak satu pun 3. boleh terlihat di resto B — termasuk angka di Saldo, isi Riwayat Kasir, 4. dan kotak masuk. | F332: F-AD-08, F-IN-10, A-10

Sheet Defect
A1: Daftar Temuan | C1: Isi satu baris per temuan. Unggah tangkapan layarnya ke folder Drive, lalu tempel tautan berkasnya di kolom Link Capture.
A2: =HYPERLINK("https://drive.google.com/drive/folders/1MonfUjlqV0aABrLDleDZhugd3pULLIOf?usp=sharing", "BUKA FOLDER CAPTURE") | D2: Unggah ke folder itu, beri nama sesuai ID temuan (DF-001.jpg), lalu Salin Tautan berkasnya dan tempel di kolom Link Capture.
A4: ID | B4: Tanggal | C4: Pelapor | D4: Versi APK | E4: Perangkat / OS | F4: Modul | G4: Peran / Akun | H4: TC Terkait | I4: Ringkasan | J4: Langkah Reproduksi | K4: Hasil Aktual | L4: Hasil Diharapkan | M4: Severity | N4: Prioritas | O4: Frekuensi | P4: Status | Q4: Ditugaskan ke | R4: Versi Perbaikan | S4: Tanggal Ditutup | T4: Link Capture | U4: Buka | V4: Catatan
U5: =IF(T5="","",HYPERLINK(T5,"Buka"))
U6: =IF(T6="","",HYPERLINK(T6,"Buka"))
U7: =IF(T7="","",HYPERLINK(T7,"Buka"))
U8: =IF(T8="","",HYPERLINK(T8,"Buka"))
U9: =IF(T9="","",HYPERLINK(T9,"Buka"))
U10: =IF(T10="","",HYPERLINK(T10,"Buka"))
U11: =IF(T11="","",HYPERLINK(T11,"Buka"))
U12: =IF(T12="","",HYPERLINK(T12,"Buka"))
U13: =IF(T13="","",HYPERLINK(T13,"Buka"))
U14: =IF(T14="","",HYPERLINK(T14,"Buka"))
U15: =IF(T15="","",HYPERLINK(T15,"Buka"))
U16: =IF(T16="","",HYPERLINK(T16,"Buka"))
... U64: =IF(T64="","",HYPERLINK(T64,"Buka"))

Sheet Prasyarat
A1: # | B1: Prasyarat | C1: Kenapa | D1: Siap?
A2: L-01 | B2: Seluruh berkas SQL di supabase/JALANKAN-INI.sql (27 bagian) sudah dijalankan | C2: Kolom yang belum ada membuat penyimpanan gagal dengan pesan yang menyesatkan
A3: L-02 | B3: Akun tersedia untuk tiap peran: Pelanggan, Kasir, Chef, Admin, Finance, Owner, Super Admin | C3: Peran diambil dari tabel employees, bukan dari pilihan di layar
A4: L-03 | B4: Minimal dua resto, dan satu akun Owner yang memiliki keduanya | C4: Isolasi antar cabang tidak bisa diuji dengan satu resto
A5: L-04 | B5: Resto uji punya bagan akun GL lengkap dan tarif PPN/service terisi | C5: Baris yang GL-nya kosong dilewati pemicu jurnal — transaksinya terjadi, catatannya tidak
A6: L-05 | B6: Rekening bank resto sudah diisi di Info Pembayaran | C6: Tombol setor mati tanpa ini
A7: L-06 | B7: Minimal 4 produk di 2 kategori, satu di antaranya punya kelompok level | C7: Diskon bundling dan varian butuh lebih dari satu menu
A8: L-07 | B8: Perangkat Android sungguhan, bukan emulator, untuk uji notifikasi dan unduhan | C8: Emulator tidak menerima FCM dengan andal
A9: L-08 | B9: Izin notifikasi dan lokasi sudah diberikan | C9: Sebagian layar berperilaku berbeda sebelum izin diberikan — itu sendiri diuji terpisah

Sheet Cara Lampirkan Capture
B1: Melampirkan tangkapan layar temuan
B3: 1. Ambil tangkapan layar di HP saat temuannya terlihat.
B4: 2. Klik tombol BUKA FOLDER CAPTURE di lembar Defect — folder Drive-nya terbuka di peramban.
B5: 3. Unggah gambarnya ke sana, beri nama sesuai ID temuan: DF-001.jpg. Kalau butuh lebih dari satu, tambahkan keterangan: DF-001-sebelum.jpg, DF-001-sesudah.jpg.
B6: 4. Klik kanan berkasnya di Drive - Bagikan - Salin tautan.
B7: 5. Tempel tautannya di kolom Link Capture pada baris temuan itu. Kolom Buka di sebelahnya berubah sendiri jadi tautan yang bisa diklik.
B9: Pastikan aksesnya "Siapa saja yang memiliki link"
B11: Tautan yang hanya bisa dibuka pemiliknya sama saja dengan tidak dilampirkan: yang membaca laporan ini nanti bukan orang yang mengunggahnya, dan dia akan berhenti di halaman minta izin.
B13: Kenapa gambarnya tidak ditempel langsung ke Excel
B15: Satu tangkapan layar HP berukuran 300-800 KB. Tiga puluh temuan sudah cukup membuat berkas ini terlalu berat untuk dikirim lewat chat mana pun — dan berkas yang tidak bisa dikirim tidak dipakai siapa-siapa.
B17: Kenapa tombolnya berupa tautan, bukan makro
B19: Tombol yang menjalankan perintah di Excel butuh makro, dan makro tidak bisa mengunggah ke Google Drive tanpa kredensial API yang harus dititipkan di dalam berkasnya — kredensial di dalam berkas yang dikirim ke banyak orang sama saja dengan diumumkan.
B21: Selain itu makro hanya hidup di berkas .xlsm: mati di Google Sheets, mati di Numbers, dan ditolak sebagian penyetelan keamanan kantor. Tautan bekerja di semuanya, dan satu klik membuka folder tempat unggahannya memang dilakukan.
